poshdate/__init__.py
poshdate/formatter.py
tests/__init__.py
tests/test_from_datetime.py
poshdate-0.3.0.dist-info/METADATA
poshdate-0.3.0.dist-info/WHEEL
poshdate-0.3.0.dist-info/license
poshdate-0.3.0.dist-info/top_level.txt
poshdate-0.3.0.dist-info/RECORD
