Metadata-Version: 2.1
Name: poshdate
Version: 0.3.0
Summary: Generate ordinal dates
Home-page: https://github.com/aj-white/poshdate
Author: Andrew White
Author-email: white-aj@outlook.com
License: MIT
Platform: Linux/Windows/MacOS
Classifier: Development Status :: 3 - Alpha
Classifier: License :: OSI Approved :: MIT License
Classifier: Operating System :: OS Independent
Classifier: Programming Language :: Python
Classifier: Programming Language :: Python :: 3
Classifier: Programming Language :: Python :: 3.6
Classifier: Programming Language :: Python :: 3.7
Classifier: Programming Language :: Python :: 3.8
Classifier: Programming Language :: Python :: 3.9
Classifier: Programming Language :: Python :: 3.10
Classifier: Topic :: Software Development :: Libraries :: Python Modules
Requires-Python: >=3.6
License-File: license
